lark_mcp/__init__.py
lark_mcp/server.py
lark_mcp-0.1.0.dist-info/LICENSE
lark_mcp-0.1.0.dist-info/METADATA
lark_mcp-0.1.0.dist-info/WHEEL
lark_mcp-0.1.0.dist-info/entry_points.txt
lark_mcp-0.1.0.dist-info/RECORD
